face_identification/__init__.py
face_identification/creat_face_bank.py
face_identification/face_identification.py
best_face_identification-1.0.0.dist-info/METADATA
best_face_identification-1.0.0.dist-info/WHEEL
best_face_identification-1.0.0.dist-info/entry_points.txt
best_face_identification-1.0.0.dist-info/top_level.txt
best_face_identification-1.0.0.dist-info/RECORD
