Metadata-Version: 2.1
Name: best_face_identification
Version: 1.0.0
Summary: This app is a face identifier. If your face is existed in face bank, you recieved True, otherwise False.
Author: javad nematollahi
Author-email: javadnematollahi92@gmail.com
Requires-Dist: insightface ==0.7.3
Requires-Dist: numpy ==1.26.4
Requires-Dist: opencv-contrib-python ==4.8.1.78
Requires-Dist: opencv-python ==4.8.1.78
Requires-Dist: opencv-python-headless ==4.8.1.78
